LICENSE.txt
NOTICE.txt
README.md
THIRD_PARTY.txt
h10awswrnglr/__init__.py
h10awswrnglr/__metadata__.py
h10awswrnglr/_config.py
h10awswrnglr/_data_types.py
h10awswrnglr/_databases.py
h10awswrnglr/_utils.py
h10awswrnglr/annotations.py
h10awswrnglr/athena/__init__.py
h10awswrnglr/athena/_cache.py
h10awswrnglr/athena/_read.py
h10awswrnglr/athena/_utils.py
h10awswrnglr/catalog/__init__.py
h10awswrnglr/catalog/_add.py
h10awswrnglr/catalog/_create.py
h10awswrnglr/catalog/_definitions.py
h10awswrnglr/catalog/_delete.py
h10awswrnglr/catalog/_get.py
h10awswrnglr/catalog/_utils.py
h10awswrnglr/chime.py
h10awswrnglr/cloudwatch.py
h10awswrnglr/data_api/__init__.py
h10awswrnglr/data_api/connector.py
h10awswrnglr/data_api/rds.py
h10awswrnglr/data_api/redshift.py
h10awswrnglr/data_quality/__init__.py
h10awswrnglr/data_quality/_create.py
h10awswrnglr/data_quality/_get.py
h10awswrnglr/data_quality/_utils.py
h10awswrnglr/dynamodb/__init__.py
h10awswrnglr/dynamodb/_delete.py
h10awswrnglr/dynamodb/_read.py
h10awswrnglr/dynamodb/_utils.py
h10awswrnglr/dynamodb/_write.py
h10awswrnglr/emr.py
h10awswrnglr/exceptions.py
h10awswrnglr/lakeformation/__init__.py
h10awswrnglr/lakeformation/_read.py
h10awswrnglr/lakeformation/_utils.py
h10awswrnglr/mysql.py
h10awswrnglr/neptune/__init__.py
h10awswrnglr/neptune/_utils.py
h10awswrnglr/neptune/client.py
h10awswrnglr/neptune/gremlin_parser.py
h10awswrnglr/neptune/neptune.py
h10awswrnglr/opensearch/__init__.py
h10awswrnglr/opensearch/_read.py
h10awswrnglr/opensearch/_utils.py
h10awswrnglr/opensearch/_write.py
h10awswrnglr/oracle.py
h10awswrnglr/postgresql.py
h10awswrnglr/py.typed
h10awswrnglr/quicksight/__init__.py
h10awswrnglr/quicksight/_cancel.py
h10awswrnglr/quicksight/_create.py
h10awswrnglr/quicksight/_delete.py
h10awswrnglr/quicksight/_describe.py
h10awswrnglr/quicksight/_get_list.py
h10awswrnglr/quicksight/_utils.py
h10awswrnglr/redshift.py
h10awswrnglr/s3/__init__.py
h10awswrnglr/s3/_copy.py
h10awswrnglr/s3/_delete.py
h10awswrnglr-2.20.0.dist-info/LICENSE.txt
h10awswrnglr-2.20.0.dist-info/METADATA
h10awswrnglr-2.20.0.dist-info/WHEEL
h10awswrnglr-2.20.0.dist-info/RECORD
