Metadata-Version: 2.1
Name: h10awswrnglr
Version: 2.20.0
Summary: Pandas on AWS.
Home-page: https://github.com/RodionG/aws-sdk-pandas
License: Apache-2.0
Keywords: pandas,aws
Author: Amazon Web Services
Requires-Python: >=3.7.1,<4.0
Classifier: License :: OSI Approved :: Apache Software License
Classifier: Programming Language :: Python :: 3
Classifier: Programming Language :: Python :: 3.8
Classifier: Programming Language :: Python :: 3.9
Classifier: Programming Language :: Python :: 3.10
Classifier: Programming Language :: Python :: 3.11
Classifier: Programming Language :: Python :: 3.10
Classifier: Programming Language :: Python :: 3.7
Classifier: Programming Language :: Python :: 3.8
Classifier: Programming Language :: Python :: 3.9
Provides-Extra: deltalake
Provides-Extra: oracle
Provides-Extra: sparql
Provides-Extra: sqlserver
Requires-Dist: SPARQLWrapper (>=1.8.5,<3.0.0) ; extra == "sparql"
Requires-Dist: backoff (>=1.10.0,<3.0.0)
Requires-Dist: boto3 (>=1.24.11,<2.0.0)
Requires-Dist: botocore (>=1.27.11,<2.0.0)
Requires-Dist: deltalake (>=0.6.4,<0.8.0) ; extra == "deltalake"
Requires-Dist: gremlinpython (==3.5.6rc1)
Requires-Dist: jsonpath-ng (>=1.5.3,<2.0.0)
Requires-Dist: numpy (>=1.21.0,<=1.23.4) ; python_full_version >= "3.7.1" and python_full_version < "3.11.0"
Requires-Dist: numpy (>=1.23.5,<2.0.0) ; python_full_version >= "3.11.0"
Requires-Dist: openpyxl (>=3.0.0,<3.1.0)
Requires-Dist: opensearch-py (>=1,<3)
Requires-Dist: oracledb (>=1.0.0,<1.1.0) ; extra == "oracle"
Requires-Dist: pandas (>=1.2.0,<2.0.0,<=1.5.1,!=1.5.0)
Requires-Dist: pg8000 (>=1.20.0,<2.0.0)
Requires-Dist: progressbar2 (>=4.0.0,<5.0.0)
Requires-Dist: pyarrow (>=2.0.0,<10.1.0)
Requires-Dist: pymysql (>=1.0.0,<2.0.0)
Requires-Dist: pyodbc (>=4.0.32,<4.1.0) ; extra == "sqlserver"
Requires-Dist: redshift-connector (>=2.0.889,<2.1.0)
Requires-Dist: requests-aws4auth (>=1.1.1,<2.0.0)
Project-URL: Documentation, https://github.com/RodionG/aws-sdk-pandas
Project-URL: Repository, https://github.com/RodionG/aws-sdk-pandas
